<?xml version="1.0" encoding="UTF-8" standalone="no"?>
<!DOCTYPE tiles-definitions PUBLIC "-//Apache Software Foundation//DTD Tiles Configuration 2.1//EN" "http://tiles.apache.org/dtds/tiles-config_2_1.dtd">
<tiles-definitions>
	<!-- <definition extends="default" name="accounts/list"> <put-attribute 
		name="body" value="/WEB-INF/views/accounts/list.jspx" /> </definition> -->
	<definition name="accounts/list" extends="content">
		<put-attribute name="body" value="/WEB-INF/views/accounts/list.jspx"></put-attribute>
	</definition>
	<definition extends="content" name="accounts/show">
		<put-attribute name="body" value="/WEB-INF/views/accounts/show.jspx" />
	</definition>
	<definition extends="content" name="accounts/create">
		<put-attribute name="body"
			value="/WEB-INF/views/accounts/create.jspx" />
	</definition>
	<definition extends="content" name="accounts/update">
		<put-attribute name="body"
			value="/WEB-INF/views/accounts/update.jspx" />
	</definition>
	<definition extends="user" name="accounts/home">
		<put-attribute name="body" value="/WEB-INF/views/accounts/home.jspx" />
	</definition>
	<definition extends="content" name="accounts/projects">
		<put-attribute name="body" value="/WEB-INF/views/accounts/projects.jspx" />
	</definition>
	<definition extends="myaccount" name="accounts/active">
		<put-attribute name="body" value="/WEB-INF/views/accounts/active.jspx" />
	</definition>
	<definition extends="myaccount" name="accounts/invalidactive">
		<put-attribute name="body" value="/WEB-INF/views/accounts/invalidactive.jspx" />
	</definition>
	<definition extends="myaccount" name="accounts/activeFailure">
		<put-attribute name="body" value="/WEB-INF/views/accounts/invalidactive.jspx" />
	</definition>
	<definition extends="content" name="accounts/redirect">
		<put-attribute name="body" value="/WEB-INF/views/accounts/redirect.jspx" />
	</definition>
</tiles-definitions>
